LICENSE-2.0.txt
MANIFEST.in
README.rst
requirements.txt
setup.cfg
setup.py
rbc_tools/__init__.py
rbc_tools/config.py
rbc_tools/connection.py
rbc_tools/egress.py
rbc_tools/instance.py
rbc_tools/inventory.py
rbc_tools/ipaddress.py
rbc_tools/network.py
rbc_tools/offering.py
rbc_tools/portforward.py
rbc_tools/sshkey.py
rbc_tools/staticnat.py
rbc_tools/template.py
rbc_tools/vpn.py
rbc_tools/zone.py
rbc_tools.egg-info/PKG-INFO
rbc_tools.egg-info/SOURCES.txt
rbc_tools.egg-info/dependency_links.txt
rbc_tools.egg-info/entry_points.txt
rbc_tools.egg-info/requires.txt
rbc_tools.egg-info/top_level.txt