Metadata-Version: 1.0
Name: rbc-tools
Version: 0.3.3
Summary: Command line tools for managing RedBridge Cloud
Home-page: http://github.com/redbridge/rbc-tools
Author: RedBridge AB
Author-email: info@redbridge.se
License: Apache 2.0
Platform: UNKNOWN
